{
  "kind": "collectionType",
  "collectionName": "viajes",
  "info": {
    "singularName": "viaje",
    "pluralName": "viajes",
    "displayName": "Viaje",
    "description": ""
  },
  "options": {
    "draftAndPublish": true
  },
  "pluginOptions": {},
  "attributes": {
    "Nombre": {
      "type": "string"
    },
    "Slug": {
      "type": "uid",
      "targetField": "Nombre"
    },
    "Descripcion": {
      "type": "richtext"
    },
    "Precio_base": {
      "type": "biginteger"
    },
    "Info_adicional": {
      "type": "string"
    },
    "Descripcion_corta": {
      "type": "string"
    },
    "Descripcion_larga": {
      "type": "richtext"
    },
    "Foto_portada": {
      "type": "media",
      "multiple": false,
      "allowedTypes": [
        "images",
        "files",
        "videos",
        "audios"
      ]
    },
    "Icono": {
      "type": "media",
      "multiple": false,
      "allowedTypes": [
        "images",
        "files",
        "videos",
        "audios"
      ]
    },
    "Galeria": {
      "type": "media",
      "multiple": true,
      "allowedTypes": [
        "images",
        "files",
        "videos",
        "audios"
      ]
    },
    "Mapa": {
      "type": "media",
      "multiple": false,
      "allowedTypes": [
        "images",
        "files",
        "videos",
        "audios"
      ]
    },
    "Archivo_PDF": {
      "type": "media",
      "multiple": false,
      "allowedTypes": [
        "images",
        "files",
        "videos",
        "audios"
      ]
    },
    "Tipo_de_viaje": {
      "type": "enumeration",
      "enum": [
        "Trekking",
        "Nature",
        "Esquí",
        "Bici",
        "Wellness",
        "Aventura"
      ]
    },
    "Estilo_de_Viaje": {
      "type": "enumeration",
      "enum": [
        "Confort",
        "Luxury",
        "Mix"
      ]
    },
    "Pais": {
      "type": "enumeration",
      "enum": [
        "España",
        "Francia-Suiza-Italia",
        "Suiza-Italia",
        "Noruega",
        "Albania",
        "Holanda",
        "Venezuela",
        "Colombia",
        "Portugal",
        "Italia",
        "México",
        "Kirguistán",
        "Islandia",
        "Marruecos",
        "Cabo Verde",
        "Mongolia",
        "Nepal",
        "Perú",
        "Nueva Zelanda",
        "Paquistán",
        "Tanzania",
        "Ecuador",
        "Turquía",
        "Costa Rica",
        "Japón",
        "Madagascar",
        "Argentina",
        "Francia-Reunión",
        "Bolivia"
      ]
    },
    "Cordillera": {
      "type": "enumeration",
      "enum": [
        "Alpes",
        "Lofoten",
        "Tian-Shan",
        "Landmannalaugar",
        "Atlas",
        "Altai",
        "Andes",
        "Himalaya",
        "Montes Raukumura y Alpes del Sur",
        "Karakorum",
        "Balcanes",
        "Macizo del Ararat",
        "Cordillera Blanca"
      ]
    },
    "Nivel_dificultad": {
      "type": "enumeration",
      "enum": [
        "Fácil",
        "Medio",
        "Experto"
      ]
    },
    "Estilo_alojamiento": {
      "type": "string"
    },
    "Regimen_alojamiento": {
      "type": "string"
    },
    "Duracion_total": {
      "type": "integer"
    },
    "Guia": {
      "type": "string"
    },
    "Transporte": {
      "type": "string"
    },
    "Forma_viajar": {
      "type": "enumeration",
      "enum": [
        "Grupo Abierto",
        "Grupo Cerrado",
        "A medida",
        "Familia",
        "Autoguiado"
      ]
    },
    "Grupo_minimo": {
      "type": "integer"
    },
    "Grupo_maximo": {
      "type": "integer"
    },
    "Temporada": {
      "type": "enumeration",
      "enum": [
        "Invierno",
        "Verano",
        "Primavera",
        "Otoño",
        "Semana Santa",
        "Navidad",
        "Verano y Primavera",
        "Invierno y Otoño"
      ]
    },
    "Continente": {
      "type": "enumeration",
      "enum": [
        "África",
        "América",
        "Asia",
        "Europa",
        "Oceanía",
        "Antártida",
        "América del Sur",
        "Centro América"
      ]
    },
    "Servicios_incluidos": {
      "type": "richtext"
    },
    "Servicios_no_incluidos": {
      "type": "richtext"
    },
    "Material_recomendado": {
      "type": "richtext"
    },
    "Staff": {
      "type": "richtext"
    },
    "Itinerario": {
      "type": "component",
      "component": "viajes.itinerario",
      "repeatable": true
    },
    "Alojamiento": {
      "type": "relation",
      "relation": "manyToMany",
      "target": "api::alojamiento.alojamiento",
      "mappedBy": "viajes"
    },
    "Seguros": {
      "type": "relation",
      "relation": "manyToMany",
      "target": "api::seguro.seguro",
      "mappedBy": "viajes"
    },
    "Transfer": {
      "type": "relation",
      "relation": "manyToMany",
      "target": "api::transfer.transfer",
      "mappedBy": "viajes"
    },
    "Descuento": {
      "type": "relation",
      "relation": "manyToMany",
      "target": "api::descuento.descuento",
      "mappedBy": "viajes"
    },
    "Salidas": {
      "type": "component",
      "component": "viajes.salida",
      "repeatable": true
    },
    "Actividades": {
      "type": "relation",
      "relation": "manyToMany",
      "target": "api::actividad.actividad",
      "mappedBy": "viajes"
    },
    "Preguntas": {
      "type": "component",
      "component": "viajes.preguntas",
      "repeatable": true
    },
    "Etiqueta_Unica": {
      "type": "string",
      "required": true,
      "unique": true
    },
    "Categoria_Unica": {
      "type": "string",
      "required": true,
      "unique": true
    },
    "Icono_Destacado": {
      "type": "media",
      "multiple": false,
      "allowedTypes": [
        "images",
        "files",
        "videos",
        "audios"
      ]
    },
    "Precio_adulto_extra": {
      "type": "decimal"
    },
    "Precio_nino_extra": {
      "type": "decimal"
    },
    "Diferente": {
      "type": "richtext"
    }
  }
}
